calc_gabrielrs/__init__.py
calc_gabrielrs/operacoes/__init__.py
calc_gabrielrs/operacoes/operacoes_avancadas.py
calc_gabrielrs/operacoes/operacoes_basicas.py
calc_gabrielrs-0.0.1.dist-info/METADATA
calc_gabrielrs-0.0.1.dist-info/WHEEL
calc_gabrielrs-0.0.1.dist-info/top_level.txt
calc_gabrielrs-0.0.1.dist-info/RECORD
