Metadata-Version: 2.1
Name: calc_gabrielrs
Version: 0.0.1
Summary: UNKNOWN
Home-page: https://github.com/gabrielrsh/criacao-pacotes-python
Author: Gabriel R.S.
Author-email: gabriel.shiota@gmail.com
License: UNKNOWN
Platform: UNKNOWN
Requires-Python: >=3.0
